django_flock-0.3.0.dist-info/DESCRIPTION.rst
django_flock-0.3.0.dist-info/METADATA
django_flock-0.3.0.dist-info/RECORD
django_flock-0.3.0.dist-info/WHEEL
django_flock-0.3.0.dist-info/metadata.json
django_flock-0.3.0.dist-info/top_level.txt
flock/__init__.py
flock/admin.py
flock/forms.py
flock/mail.py
flock/models.py
flock/moochers.py
flock/urls.py
flock/views.py
flock/locale/de/LC_MESSAGES/django.mo
flock/locale/de/LC_MESSAGES/django.po
flock/migrations/0001_initial.py
flock/migrations/0002_auto_20160301_1326.py
flock/migrations/0003_donation_payment_service_provider.py
flock/migrations/0004_project_is_reward_required.py
flock/migrations/__init__.py
flock/templates/flock/base.html
flock/templates/flock/donate_fail.html
flock/templates/flock/donate_payment_provider.html
flock/templates/flock/donate_thanks.html
flock/templates/flock/form.html
flock/templates/flock/no_project.html
flock/templates/flock/thanks_mail.txt
