Metadata-Version: 2.0
Name: django-flock
Version: 0.3.0
Summary: Simple crowdfunding for Django
Home-page: https://github.com/matthiask/django-flock/
Author: Matthias Kestenholz
Author-email: mk@feinheit.ch
License: MIT License
Platform: OS Independent
Classifier: Development Status :: 4 - Beta
Classifier: Environment :: Web Environment
Classifier: Framework :: Django
Classifier: Intended Audience :: Developers
Classifier: License :: OSI Approved :: BSD License
Classifier: Operating System :: OS Independent
Classifier: Programming Language :: Python
Classifier: Programming Language :: Python :: 3
Classifier: Topic :: Internet :: WWW/HTTP :: Dynamic Content
Classifier: Topic :: Software Development
Classifier: Topic :: Software Development :: Libraries :: Application Frameworks
Requires-Dist: django-mooch
